CHANGES.txt
LICENSE.txt
MANIFEST.in
README.txt
setup.py
src/m01/__init__.py
src/m01.session.egg-info/PKG-INFO
src/m01.session.egg-info/SOURCES.txt
src/m01.session.egg-info/dependency_links.txt
src/m01.session.egg-info/namespace_packages.txt
src/m01.session.egg-info/not-zip-safe
src/m01.session.egg-info/requires.txt
src/m01.session.egg-info/top_level.txt
src/m01/session/README.txt
src/m01/session/__init__.py
src/m01/session/client.py
src/m01/session/client.txt
src/m01/session/configure.zcml
src/m01/session/interfaces.py
src/m01/session/meta.zcml
src/m01/session/session.py
src/m01/session/tests.py
src/m01/session/zcml.py
src/m01/session/testing/__init__.py